statsd-plugin/StatsdPlugin.py
statsd-plugin/__init__.py
statsd_plugin/StatsdPlugin.py
statsd_plugin/__init__.py
statsd_plugin-0.1.1.dist-info/DESCRIPTION.rst
statsd_plugin-0.1.1.dist-info/METADATA
statsd_plugin-0.1.1.dist-info/RECORD
statsd_plugin-0.1.1.dist-info/WHEEL
statsd_plugin-0.1.1.dist-info/metadata.json
statsd_plugin-0.1.1.dist-info/top_level.txt
