Metadata-Version: 2.0
Name: statsd-plugin
Version: 0.1.1
Summary: A simple library to write plugins for statsd
Home-page: https://github.com/h4xr/statsd-plugin
Author: Saurabh Badhwar
Author-email: sbsaurabhbadhwar9@gmail.com
License: MIT
Keywords: statsd plugin development
Platform: UNKNOWN
Classifier: Development Status :: 3 - Alpha
Classifier: Intended Audience :: Developers
Classifier: Topic :: Software Development :: Libraries
Classifier: License :: OSI Approved :: MIT License
Classifier: Programming Language :: Python :: 2.7
Requires-Dist: statsd
